secret_files/__init__.py
secret_files/methods.py
secret_files-0.0.1.dist-info/LICENSE.md
secret_files-0.0.1.dist-info/METADATA
secret_files-0.0.1.dist-info/WHEEL
secret_files-0.0.1.dist-info/top_level.txt
secret_files-0.0.1.dist-info/RECORD
