Metadata-Version: 2.1
Name: secret-files
Version: 0.0.1
Summary: # Secret Files
Author-email: Justin Slay <justin.slay@gmail.com>
Project-URL: Source, https://github.com/jslay88/secret_files
Project-URL: Homepage, https://github.com/jslay88/secret_files
Project-URL: Bug Tracker, https://github.com/jslay88/secret_files/issues
Classifier: Development Status :: 5 - Production/Stable
Classifier: Intended Audience :: Developers
Classifier: Intended Audience :: Information Technology
Classifier: License :: OSI Approved :: MIT License
Classifier: Programming Language :: Python :: 3.0
Classifier: Programming Language :: Python :: 3.1
Classifier: Programming Language :: Python :: 3.2
Classifier: Programming Language :: Python :: 3.3
Classifier: Programming Language :: Python :: 3.4
Classifier: Programming Language :: Python :: 3.5
Classifier: Programming Language :: Python :: 3.6
Classifier: Programming Language :: Python :: 3.7
Classifier: Programming Language :: Python :: 3.8
Classifier: Programming Language :: Python :: 3.9
Classifier: Programming Language :: Python :: 3.10
Classifier: Programming Language :: Python :: 3.11
Classifier: Topic :: Software Development :: Libraries
Classifier: Topic :: Software Development :: Libraries :: Python Modules
Classifier: Typing :: Typed
Requires-Python: >=3
License-File: LICENSE.md
Provides-Extra: build
Requires-Dist: build ; extra == 'build'
Provides-Extra: dev
Requires-Dist: bandit ; extra == 'dev'
Requires-Dist: black ; extra == 'dev'
Requires-Dist: coverage ; extra == 'dev'
Requires-Dist: diff-cover ; extra == 'dev'
Requires-Dist: flake8 ; extra == 'dev'
Requires-Dist: isort ; extra == 'dev'
Requires-Dist: pre-commit ; extra == 'dev'
Requires-Dist: pytest (>=2.7.3) ; extra == 'dev'
Requires-Dist: tox ; extra == 'dev'
Provides-Extra: test
Requires-Dist: tox ; extra == 'test'
